setup.py
kvkit/__init__.py
kvkit/exceptions.py
kvkit/graph.py
kvkit/query.py
kvkit/tests.py
kvkit.egg-info/PKG-INFO
kvkit.egg-info/SOURCES.txt
kvkit.egg-info/dependency_links.txt
kvkit.egg-info/top_level.txt
kvkit/backends/__init__.py
kvkit/backends/berkeleydb.py
kvkit/backends/forest.py
kvkit/backends/helpers.py
kvkit/backends/kyoto.py
kvkit/backends/leveldb.py
kvkit/backends/rocks.py
kvkit/backends/sophia.py
kvkit/backends/sqlite4.py