Metadata-Version: 1.1
Name: kvkit
Version: 0.1.2
Summary: high-level python toolkit for ordered key/value stores
Home-page: http://github.com/coleifer/kvkit/
Author: Charles Leifer
Author-email: coleifer@gmail.com
License: UNKNOWN
Platform: UNKNOWN
Classifier: Development Status :: 4 - Beta
Classifier: Environment :: Web Environment
Classifier: Intended Audience :: Developers
Classifier: License :: OSI Approved :: MIT License
Classifier: Operating System :: OS Independent
Classifier: Programming Language :: Python
